agatedbf/__init__.py
agatedbf/table.py
agate_dbf-0.2.3.dist-info/AUTHORS.rst
agate_dbf-0.2.3.dist-info/COPYING
agate_dbf-0.2.3.dist-info/METADATA
agate_dbf-0.2.3.dist-info/WHEEL
agate_dbf-0.2.3.dist-info/top_level.txt
agate_dbf-0.2.3.dist-info/RECORD
